pretalx/__init__.py
pretalx/__main__.py
pretalx/celery_app.py
pretalx/settings.py
pretalx/urls.py
pretalx/wsgi.py
pretalx/agenda/__init__.py
pretalx/agenda/apps.py
pretalx/agenda/context_processors.py
pretalx/agenda/phrases.py
pretalx/agenda/recording.py
pretalx/agenda/rules.py
pretalx/agenda/signals.py
pretalx/agenda/tasks.py
pretalx/agenda/urls.py
pretalx/agenda/management/__init__.py
pretalx/agenda/management/commands/__init__.py
pretalx/agenda/management/commands/export_schedule_html.py
pretalx/agenda/templates/agenda/base.html
pretalx/agenda/templates/agenda/changelog.html
pretalx/agenda/templates/agenda/changelog_block.html
pretalx/agenda/templates/agenda/featured.html
pretalx/agenda/templates/agenda/feedback.html
pretalx/agenda/templates/agenda/feedback_form.html
pretalx/agenda/templates/agenda/schedule.html
pretalx/agenda/templates/agenda/schedule.xcal
pretalx/agenda/templates/agenda/schedule.xcal.license
pretalx/agenda/templates/agenda/schedule.xml
pretalx/agenda/templates/agenda/schedule.xml.license
pretalx/agenda/templates/agenda/schedule_nojs.html
pretalx/agenda/templates/agenda/session_block.html
pretalx/agenda/templates/agenda/speaker.html
pretalx/agenda/templates/agenda/speaker_block.html
pretalx/agenda/templates/agenda/speakers.html
pretalx/agenda/templates/agenda/talk.html
pretalx/agenda/templates/agenda/feed/description.html
pretalx/agenda/templates/agenda/includes/submission_resource.html
pretalx/agenda/views/__init__.py
pretalx/agenda/views/featured.py
pretalx/agenda/views/feed.py
pretalx/agenda/views/schedule.py
pretalx/agenda/views/speaker.py
pretalx/agenda/views/talk.py
pretalx/agenda/views/utils.py
pretalx/agenda/views/widget.py
pretalx/api/__init__.py
pretalx/api/apps.py
pretalx/api/documentation.py
pretalx/api/exceptions.py
pretalx/api/pagination.py
pretalx/api/permissions.py
pretalx/api/shims.py
pretalx/api/urls.py
pretalx/api/versions.py
pretalx/api/filters/__init__.py
pretalx/api/filters/review.py
pretalx/api/filters/schedule.py
pretalx-2025.2.2.dist-info/licenses/LICENSE
pretalx-2025.2.2.dist-info/METADATA
pretalx-2025.2.2.dist-info/WHEEL
pretalx-2025.2.2.dist-info/top_level.txt
pretalx-2025.2.2.dist-info/RECORD
