Metadata-Version: 2.4
Name: pretalx
Version: 2025.2.2
Summary: Conference organisation: CfPs, scheduling, much more
Author-email: Tobias Kunze <r@rixx.de>
Maintainer-email: Tobias Kunze <r@rixx.de>
License-Expression: AGPL-3.0-only
Project-URL: Homepage, https://pretalx.com
Project-URL: Documentation, https://docs.pretalx.org
Project-URL: Repository, https://github.com/pretalx/pretalx
Project-URL: Changelog, https://docs.pretalx.org/changelog/
Project-URL: Issues, https://github.com/pretalx/pretalx/issues
Keywords: conference,event,schedule,talk,cfp
Classifier: Development Status :: 5 - Production/Stable
Classifier: Environment :: Web Environment
Classifier: Framework :: Django :: 5.2
Classifier: Intended Audience :: Developers
Classifier: Intended Audience :: Other Audience
Classifier: Programming Language :: Python :: 3.10
Classifier: Programming Language :: Python :: 3.11
Classifier: Programming Language :: Python :: 3.12
Classifier: Programming Language :: Python :: 3.13
Classifier: Programming Language :: Python :: 3.14
Classifier: Topic :: Internet :: WWW/HTTP :: Dynamic Content
Requires-Python: >=3.10
License-File: LICENSE
Requires-Dist: beautifulsoup4[lxml]~=4.14.0
Requires-Dist: bleach~=6.3.0
Requires-Dist: celery~=5.5.0
Requires-Dist: css_inline~=0.18.0
Requires-Dist: cssutils~=2.11.0
Requires-Dist: defusedcsv~=3.0.0
Requires-Dist: defusedxml~=0.7.0
Requires-Dist: diff-match-patch==20241021
Requires-Dist: Django[argon2]~=5.2.2
Requires-Dist: django-context-decorator
Requires-Dist: django-countries~=8.1.0
Requires-Dist: django-csp~=4.0.0
Requires-Dist: django-filter==25.2
Requires-Dist: django-formset-js-improved==0.5.0.4
Requires-Dist: django-formtools~=2.5.1
Requires-Dist: django-hierarkey~=2.0.1
Requires-Dist: django-i18nfield~=1.11.0
Requires-Dist: django-minify-html~=1.14.0
Requires-Dist: django-scopes~=2.0.0
Requires-Dist: django-tables2~=2.8.0
Requires-Dist: djangorestframework~=3.16.0
Requires-Dist: drf-flex-fields~=1.0.0
Requires-Dist: Markdown~=3.10.0
Requires-Dist: Pillow~=12.0.0
Requires-Dist: publicsuffixlist~=1.0.0
Requires-Dist: python-dateutil~=2.9.0
Requires-Dist: qrcode~=8.0
Requires-Dist: reportlab~=4.4.0
Requires-Dist: requests~=2.32.0
Requires-Dist: rules~=3.5.0
Requires-Dist: urlman~=2.0.1
Requires-Dist: vobject~=0.9.0
Requires-Dist: whitenoise[brotli]~=6.11.0
Requires-Dist: zxcvbn~=4.5.0
Provides-Extra: dev
Requires-Dist: black; extra == "dev"
Requires-Dist: build; extra == "dev"
Requires-Dist: check-manifest; extra == "dev"
Requires-Dist: coverage; extra == "dev"
Requires-Dist: django-watchfiles; extra == "dev"
Requires-Dist: djhtml; extra == "dev"
Requires-Dist: flake8; extra == "dev"
Requires-Dist: flake8-bugbear; extra == "dev"
Requires-Dist: freezegun; extra == "dev"
Requires-Dist: isort; extra == "dev"
Requires-Dist: jsonschema; extra == "dev"
Requires-Dist: pytest; extra == "dev"
Requires-Dist: pytest-cov; extra == "dev"
Requires-Dist: pytest-django; extra == "dev"
Requires-Dist: pytest-mock; extra == "dev"
Requires-Dist: pytest-sugar; extra == "dev"
Requires-Dist: pytest-xdist; extra == "dev"
Requires-Dist: responses; extra == "dev"
Requires-Dist: twine; extra == "dev"
Requires-Dist: urllib3; extra == "dev"
Provides-Extra: devdocs
Requires-Dist: drf-spectacular~=0.29.0; extra == "devdocs"
Requires-Dist: sphinx<9.0; extra == "devdocs"
Requires-Dist: sphinx-autobuild; extra == "devdocs"
Requires-Dist: sphinx-autodoc-typehints; extra == "devdocs"
Requires-Dist: sphinx-copybutton; extra == "devdocs"
Requires-Dist: sphinxcontrib-django; extra == "devdocs"
Requires-Dist: sphinxcontrib-httpdomain; extra == "devdocs"
Requires-Dist: sphinxcontrib-spelling; extra == "devdocs"
Provides-Extra: postgres
Requires-Dist: psycopg2-binary~=2.9.0; extra == "postgres"
Provides-Extra: redis
Requires-Dist: redis~=7.1.0; extra == "redis"
Dynamic: license-file
